Metadata-Version: 2.1
Name: premsir
Version: 1.0.0
Summary: Programming in a nutshell for grade 11.
Home-page: https://github.com/ISROHarsh/premsir
Download-URL: https://github.com/ISROHarsh/premsir/archive/refs/tags/v1.0.0.tar.gz
Author: Prem Kumar Singh
License: MIT License
Classifier: Programming Language :: Python
Classifier: Programming Language :: Python :: 2
Classifier: Programming Language :: Python :: 2.7
Classifier: Programming Language :: Python :: 3
Classifier: Programming Language :: Python :: 3.5
Classifier: Programming Language :: Python :: 3.6
Classifier: Programming Language :: Python :: 3.7
Classifier: Programming Language :: Python :: 3.8
Classifier: Programming Language :: Python :: 3.9
Classifier: Programming Language :: Python :: 3.10
License-File: LICENSE
